README.md
setup.py
bugra_deneme.egg-info/PKG-INFO
bugra_deneme.egg-info/SOURCES.txt
bugra_deneme.egg-info/dependency_links.txt
bugra_deneme.egg-info/requires.txt
bugra_deneme.egg-info/top_level.txt
power_api/__init__.py
power_api/command.py
power_api/definitions.py
power_api/event.py
power_api/exceptions.py
power_api/power_api.py