Metadata-Version: 1.0
Name: bugra-deneme
Version: 0.1.2
Summary: power management service python api
Home-page: https://github.com/sixfab/sixfab-power-python-api
Author: Yasin Kaya
Author-email: yasinkaya.121@gmail.com
License: MIT
Platform: UNKNOWN
